LICENSE.rst
README.txt
pyproject.toml
setup.cfg
setup.py
my_HWs_for_py_123/__init__.py
my_HWs_for_py_123.egg-info/PKG-INFO
my_HWs_for_py_123.egg-info/SOURCES.txt
my_HWs_for_py_123.egg-info/dependency_links.txt
my_HWs_for_py_123.egg-info/top_level.txt
my_HWs_for_py_123/week1/__init__.py
my_HWs_for_py_123/week1/task1_1.py
my_HWs_for_py_123/week1/task1_2.py
my_HWs_for_py_123/week1/task1_3.py
my_HWs_for_py_123/week1/task1_4.py
my_HWs_for_py_123/week1/task1_5.py
my_HWs_for_py_123/week1/task3_1_Update.py
my_HWs_for_py_123/week1/my/HW1.py
my_HWs_for_py_123/week1/my/__init__.py
my_HWs_for_py_123/week1/my/q.py
my_HWs_for_py_123/week2/Task2_5.py
my_HWs_for_py_123/week2/__init__.py
my_HWs_for_py_123/week2/task2_1.py
my_HWs_for_py_123/week2/task2_2.py
my_HWs_for_py_123/week2/task2_3.py
my_HWs_for_py_123/week2/task2_4.py
my_HWs_for_py_123/week2/my/__init__.py
my_HWs_for_py_123/week2/my/find_util.py
my_HWs_for_py_123/week2/my/task1.py
my_HWs_for_py_123/week2/my/task2.py
my_HWs_for_py_123/week2/my/task3.py
my_HWs_for_py_123/week2/my/task4.py
my_HWs_for_py_123/week2/my/task_5.py
my_HWs_for_py_123/week2/my/for_4_task/__init__.py
my_HWs_for_py_123/week2/my/for_4_task/dir1/__init__.py
my_HWs_for_py_123/week2/my/for_4_task/dir1/dir2/__init__.py
my_HWs_for_py_123/week2/my/for_4_task/dir1/dir2/dir5/__init__.py
my_HWs_for_py_123/week2/my/for_4_task/dir4/__init__.py
my_HWs_for_py_123/week3/__init__.py
my_HWs_for_py_123/week3/my/__init__.py
my_HWs_for_py_123/week3/my/task1.py
my_HWs_for_py_123/week3/my/task2.py
my_HWs_for_py_123/week4/__init__.py
my_HWs_for_py_123/week5/__init__.py
my_HWs_for_py_123/week6/__init__.py
my_HWs_for_py_123/week7/__init__.py