Metadata-Version: 1.0
Name: my-HWs-for-py-123
Version: 0.0.4
Summary: It's HWs package
Home-page: https://github.com/dvts25/HWs
Author: dvts
Author-email: denys_voloshyn1@email.com
License: UNKNOWN
Platform: UNKNOWN
